haver/__init__.py
haver/haver.py
haver/haver_maps.py
haver/res/by-nc-sa.eu.svg
haver/res/haver.jpg
haver/tests/__init__.py
haver/tests/test_all.py
haver-0.7.0.dist-info/LICENSE.md
haver-0.7.0.dist-info/METADATA
haver-0.7.0.dist-info/WHEEL
haver-0.7.0.dist-info/top_level.txt
haver-0.7.0.dist-info/RECORD
