Metadata-Version: 2.2
Name: haver
Version: 0.7.0
Summary: A Python wrapper to Haver Analytics' RESTful API.
Home-page: https://github.com/LucaMingarelli/haver
Author: Luca Mingarelli
Author-email: lucamingarelli@me.com
License: CC BY-NC-SA 4.0
Classifier: Programming Language :: Python :: 3
Classifier: License :: OSI Approved :: MIT License
Classifier: Operating System :: OS Independent
Requires-Python: >=3.6
License-File: LICENSE.md
Requires-Dist: pandas
Requires-Dist: requests
Dynamic: author
Dynamic: author-email
Dynamic: classifier
Dynamic: description
Dynamic: description-content-type
Dynamic: home-page
Dynamic: license
Dynamic: requires-dist
Dynamic: requires-python
Dynamic: summary
